gaussFilter/__init__.py
gaussFilter/gaussFilter.py
gaussFilter-1.0.1.dist-info/LICENSE
gaussFilter-1.0.1.dist-info/METADATA
gaussFilter-1.0.1.dist-info/WHEEL
gaussFilter-1.0.1.dist-info/top_level.txt
gaussFilter-1.0.1.dist-info/RECORD
