Metadata-Version: 2.1
Name: gaussFilter
Version: 1.0.1
Summary: A package for applying Gaussian filter to images
Home-page: https://github.com/divagarn/gaussFilter.git
Author: Divagar N
Author-email: divagar2kn@gmail.com
License: MIT
License-File: LICENSE
Requires-Dist: numpy
Requires-Dist: opencv-python
